ps4_updates/__init__.py
ps4_updates/pkg.py
ps4_updates/title.py
ps4_updates-1.1.0.dist-info/METADATA
ps4_updates-1.1.0.dist-info/WHEEL
ps4_updates-1.1.0.dist-info/RECORD
