Metadata-Version: 2.4
Name: ps4_updates
Version: 1.1.0
Summary: A simple package for accessing PS4 title update information
Project-URL: Homepage, https://github.com/andshrew/PS4-Updates-Python
Project-URL: Repository, https://github.com/andshrew/PS4-Updates-Python.git
Project-URL: GitHub, https://github.com/andshrew/PS4-Updates-Python
Project-URL: Issues, https://github.com/andshrew/PS4-Updates-Python/issues
Project-URL: Changelog, https://github.com/andshrew/PS4-Updates-Python/releases
Author-email: andshrew <7409326+andshrew@users.noreply.github.com>
License-Expression: MIT
Classifier: License :: OSI Approved :: MIT License
Classifier: Operating System :: OS Independent
Classifier: Programming Language :: Python :: 3
Requires-Python: >=3.8
Requires-Dist: requests>=2.31
